texttovoice/__init__.py
texttovoice-0.1.dist-info/METADATA
texttovoice-0.1.dist-info/RECORD
texttovoice-0.1.dist-info/WHEEL
texttovoice-0.1.dist-info/top_level.txt
