Metadata-Version: 2.1
Name: texttovoice
Version: 0.1
Summary: Text to voice project
Home-page: http://github.com/mmehedin/TextToVoice.git
Author: Mihai Mehe
Author-email: mmehedin@uncc.edu
License: MIT
Platform: UNKNOWN
